minioc/__init__.py
minioc-1.2.1.dist-info/LICENSE
minioc-1.2.1.dist-info/METADATA
minioc-1.2.1.dist-info/WHEEL
minioc-1.2.1.dist-info/top_level.txt
minioc-1.2.1.dist-info/RECORD
