Metadata-Version: 2.1
Name: minioc
Version: 1.2.1
Summary: A mini IOC framework
Home-page: https://github.com/WillFr/rest-helpers
Author: Guillaume Grosbois
Author-email: grosbois.guillaume@gmail.com
License: UNKNOWN
Platform: UNKNOWN
Classifier: Programming Language :: Python :: 3.5
Classifier: Operating System :: OS Independent
Requires-Dist: setuptools (>=0.5)
